fileschemavalidator
