Metadata-Version: 2.1
Name: FileSchemaValidator
Version: 0.0.2
Summary: This module provides a powerful and extensible solution for validating CSV files against customizable schemas in Python
Home-page: https://github.com/henriqueortiz/FileSchemaValidator
Author: Henrique Ortiz
Author-email: henriqueortiz.1@gmail.com
